shuffle_email_rules/__init__.py
shuffle_email_rules/evaluate.py
shuffle_email_rules/main.py
shuffle_email_rules/lib/go.mod
shuffle_email_rules/lib/go.sum
shuffle_email_rules/lib/libhello.h
shuffle_email_rules/lib/libhello.so
shuffle_email_rules/lib/main.go
shuffle_email_rules-0.5.dist-info/METADATA
shuffle_email_rules-0.5.dist-info/WHEEL
shuffle_email_rules-0.5.dist-info/top_level.txt
shuffle_email_rules-0.5.dist-info/RECORD
