Metadata-Version: 2.1
Name: shuffle-email-rules
Version: 0.5
Summary: An open-source language for email filtering rules.
Author: Aditya
Author-email: aditya@shuffler.io
